{"cameraMode":{"drawMode":0,"name":"Shaded","section":"Shading Mode"},"sceneLighting":true,"audioPlay":false,"sceneViewState":{"showFog":true,"showMaterialUpdate":false,"showSkybox":true,"showFlares":true,"showImageEffects":true,"showParticleSystems":true},"in2DMode":false,"pivot":{"x":0.008504574187099934,"y":0.0833333358168602,"z":-1.0857391357421876},"rotation":{"x":0.5014705657958984,"y":-0.34906497597694399,"z":0.23120425641536714,"w":0.7571246027946472},"size":2.770524263381958,"orthographic":false}